iiif_prezi/__init__.py
iiif_prezi/_version.py
iiif_prezi/factory.py
iiif_prezi/factory_11.py
iiif_prezi/json_with_order.py
iiif_prezi/loader.py
iiif_prezi/util.py
iiif_prezi/contexts/context_10.json
iiif_prezi/contexts/context_20.json
iiif_prezi/contexts/context_21.json
iiif_prezi-0.3.0.dist-info/LICENSE.md
iiif_prezi-0.3.0.dist-info/METADATA
iiif_prezi-0.3.0.dist-info/WHEEL
iiif_prezi-0.3.0.dist-info/top_level.txt
iiif_prezi-0.3.0.dist-info/RECORD
