Metadata-Version: 2.1
Name: iiif-prezi
Version: 0.3.0
Summary: IIIF Presentation API implementation
Home-page: https://github.com/IIIF/iiif-prezi
Author: Rob Sanderson, Simeon Warner
Author-email: UNKNOWN
License: LICENSE.md
Platform: UNKNOWN
Classifier: Development Status :: 4 - Beta
Classifier: Intended Audience :: Developers
Classifier: License :: OSI Approved :: Apache Software License
Classifier: Operating System :: OS Independent
Classifier: Programming Language :: Python
Classifier: Programming Language :: Python :: 2
Classifier: Programming Language :: Python :: 2.7
Classifier: Programming Language :: Python :: 3
Classifier: Programming Language :: Python :: 3.4
Classifier: Programming Language :: Python :: 3.5
Classifier: Programming Language :: Python :: 3.6
Classifier: Topic :: Internet :: WWW/HTTP
Classifier: Topic :: Multimedia :: Graphics :: Graphics Conversion
Classifier: Topic :: Software Development :: Libraries :: Python Modules
Classifier: Environment :: Web Environment
Requires-Dist: lxml
Requires-Dist: Pillow
Requires-Dist: pyld
